polarityjam/__init__.py
polarityjam/__main__.py
polarityjam/argument_parsing.py
polarityjam/commandline.py
polarityjam/polarityjam_logging.py
polarityjam/settings.py
polarityjam/compute/__init__.py
polarityjam/compute/compute.py
polarityjam/compute/corner.py
polarityjam/compute/neighborhood.py
polarityjam/compute/shape.py
polarityjam/compute/statistics.py
polarityjam/controller/__init__.py
polarityjam/controller/collector.py
polarityjam/controller/extractor.py
polarityjam/controller/plotter.py
polarityjam/controller/segmenter.py
polarityjam/model/__init__.py
polarityjam/model/collection.py
polarityjam/model/image.py
polarityjam/model/masks.py
polarityjam/model/moran.py
polarityjam/model/parameter.py
polarityjam/model/properties.py
polarityjam/model/weights.py
polarityjam/segmentation/__init__.py
polarityjam/segmentation/cellpose.py
polarityjam/segmentation/cellpose.yml
polarityjam/segmentation/deepcell.py
polarityjam/segmentation/deepcell.yml
polarityjam/segmentation/microsam.py
polarityjam/segmentation/microsam.yml
polarityjam/segmentation/sam.py
polarityjam/segmentation/sam.yml
polarityjam/test/__init__.py
polarityjam/test/__main__.py
polarityjam/test/test_all.py
polarityjam/test/test_common.py
polarityjam/test/test_config.py
polarityjam/test/integration/__init__.py
polarityjam/test/integration/test_commandline.py
polarityjam/test/integration/test_extraction.py
polarityjam/test/integration/test_masks.py
polarityjam/test/integration/test_notebook.py
polarityjam/test/integration/test_properties.py
polarityjam/test/resources/060721_EGM2_18dyn_02_small_seg.npy
polarityjam/test/resources/060721_EGM2_18dyn_02_small_seg_nuc.npy
polarityjam/test/resources/data.zip
polarityjam/test/resources/parameters_extract_all.yml
polarityjam/test/resources/parameters_extract_no_intensity.yml
polarityjam/test/resources/parameters_extract_no_morphology.yml
polarityjam/test/resources/parameters_extract_no_polarity.yml
polarityjam/test/resources/parameters_extract_no_topology.yml
polarityjam-0.4.2.dist-info/licenses/LICENSE
polarityjam-0.4.2.dist-info/METADATA
polarityjam-0.4.2.dist-info/WHEEL
polarityjam-0.4.2.dist-info/entry_points.txt
polarityjam-0.4.2.dist-info/top_level.txt
polarityjam-0.4.2.dist-info/RECORD
